nonebot_plugin_bugku/__init__.py
nonebot_plugin_bugku/config.py
nonebot_plugin_bugku/cron_send.py
nonebot_plugin_bugku/data_source.py
nonebot_plugin_bugku-0.1.2.dist-info/METADATA
nonebot_plugin_bugku-0.1.2.dist-info/WHEEL
nonebot_plugin_bugku-0.1.2.dist-info/top_level.txt
nonebot_plugin_bugku-0.1.2.dist-info/RECORD
