Metadata-Version: 2.1
Name: nonebot-plugin-bugku
Version: 0.1.2
Summary: 用于检测bugku的公开AWD房间
Home-page: https://github.com/KagamigawaMeguri/nonebot_plugin_bugku
Author: kagamigawa
Author-email: kanomeguri@outlook.com
License: MIT
Platform: UNKNOWN
Classifier: License :: OSI Approved :: MIT License
Classifier: Programming Language :: Python
Classifier: Programming Language :: Python :: 3
Classifier: Programming Language :: Python :: 3.6
Classifier: Programming Language :: Python :: Implementation :: CPython
Classifier: Programming Language :: Python :: Implementation :: PyPy
Requires-Python: >=3.7.0
Requires-Dist: Path
Requires-Dist: pydantic
Requires-Dist: dataclasses
Requires-Dist: httpx
Requires-Dist: bs4
Requires-Dist: lxml
